
                    {
                        "metadata": {
    "streams": [
        {
            "index": 0,
            "codec_name": "pcm_s16le",
            "codec_long_name": "PCM signed 16-bit little-endian",
            "codec_type": "audio",
            "codec_tag_string": "[1][0][0][0]",
            "codec_tag": "0x0001",
            "sample_fmt": "s16",
            "sample_rate": "44100",
            "channels": 2,
            "bits_per_sample": 16,
            "initial_padding": 0,
            "r_frame_rate": "0/0",
            "avg_frame_rate": "0/0",
            "time_base": "1/44100",
            "duration_ts": 2323340,
            "duration": "52.683447",
            "bit_rate": "1411200",
            "disposition": {
                "default": 0,
                "dub": 0,
                "original": 0,
                "comment": 0,
                "lyrics": 0,
                "karaoke": 0,
                "forced": 0,
                "hearing_impaired": 0,
                "visual_impaired": 0,
                "clean_effects": 0,
                "attached_pic": 0,
                "timed_thumbnails": 0,
                "non_diegetic": 0,
                "captions": 0,
                "descriptions": 0,
                "metadata": 0,
                "dependent": 0,
                "still_image": 0
            }
        }
    ],
    "format": {
        "filename": "/Users/austinfranklin/Desktop/School/Dissertation Documents/Dissertation Lecture Documentation/Bill Audio/2022-11-16 Austin Franklin, composition-05 Introducing Sing! and Bloom.wav",
        "nb_streams": 1,
        "nb_programs": 0,
        "format_name": "wav",
        "format_long_name": "WAV / WAVE (Waveform Audio)",
        "duration": "52.683447",
        "size": "9369034",
        "bit_rate": "1422691",
        "probe_score": 99,
        "tags": {
            "encoded_by": "Pro Tools",
            "originator_reference": "aaycQ!qAYsUk",
            "date": "2022-11-30",
            "creation_time": "15:26:25",
            "time_reference": "112713409",
            "umid": "0x060A2B340101010501010F1013000000E4B2690FEA0980005D26AF25C3E13E00"
        }
    }
},
                        "path": "/Users/austinfranklin/Desktop/School/Dissertation Documents/Dissertation Lecture Documentation/Bill Audio/2022-11-16 Austin Franklin, composition-05 Introducing Sing! and Bloom.wav",
                        "analysis": [ 0.578667, 1.03757, 0.587767, 3.77765, 0.0415846, 96.6294, 0.000829352, 0.00367778, 0.648754, 0.5375 ]
                    }
