
                    {
                        "metadata": {
    "streams": [
        {
            "index": 0,
            "codec_name": "pcm_s24le",
            "codec_long_name": "PCM signed 24-bit little-endian",
            "codec_type": "audio",
            "codec_tag_string": "[1][0][0][0]",
            "codec_tag": "0x0001",
            "sample_fmt": "s32",
            "sample_rate": "48000",
            "channels": 2,
            "bits_per_sample": 24,
            "initial_padding": 0,
            "r_frame_rate": "0/0",
            "avg_frame_rate": "0/0",
            "time_base": "1/48000",
            "duration_ts": 14548992,
            "duration": "303.104000",
            "bit_rate": "2304000",
            "bits_per_raw_sample": "24",
            "disposition": {
                "default": 0,
                "dub": 0,
                "original": 0,
                "comment": 0,
                "lyrics": 0,
                "karaoke": 0,
                "forced": 0,
                "hearing_impaired": 0,
                "visual_impaired": 0,
                "clean_effects": 0,
                "attached_pic": 0,
                "timed_thumbnails": 0,
                "non_diegetic": 0,
                "captions": 0,
                "descriptions": 0,
                "metadata": 0,
                "dependent": 0,
                "still_image": 0
            }
        }
    ],
    "format": {
        "filename": "/Users/austinfranklin/Desktop/Classical-Album/Flower of the Sun/Flower of the Sun.wav",
        "nb_streams": 1,
        "nb_programs": 0,
        "format_name": "wav",
        "format_long_name": "WAV / WAVE (Waveform Audio)",
        "duration": "303.104000",
        "size": "87757642",
        "bit_rate": "2316238",
        "probe_score": 99,
        "tags": {
            "encoded_by": "Pro Tools",
            "originator_reference": "aaODPRXCKTVk",
            "date": "2022-07-06",
            "creation_time": "19:34:04",
            "time_reference": "718798848",
            "umid": "0x060A2B340101010501010F1013000000FB64731AE9768000C07B3D90EAB8204C"
        }
    }
},
                        "path": "/Users/austinfranklin/Desktop/Classical-Album/Flower of the Sun/Flower of the Sun.wav",
                        "analysis": [ 0.242057, 4.99236, 0.0969029, 35.3722, 0.331513, 418.248, 0.0228359, 0.0689969, 0.123775, 0.255208 ]
                    }
