
                    {
                        "metadata": {
    "streams": [
        {
            "index": 0,
            "codec_name": "pcm_s16le",
            "codec_long_name": "PCM signed 16-bit little-endian",
            "codec_type": "audio",
            "codec_tag_string": "[1][0][0][0]",
            "codec_tag": "0x0001",
            "sample_fmt": "s16",
            "sample_rate": "22050",
            "channels": 2,
            "bits_per_sample": 16,
            "initial_padding": 0,
            "r_frame_rate": "0/0",
            "avg_frame_rate": "0/0",
            "time_base": "1/22050",
            "duration_ts": 1029606,
            "duration": "46.694150",
            "bit_rate": "705600",
            "disposition": {
                "default": 0,
                "dub": 0,
                "original": 0,
                "comment": 0,
                "lyrics": 0,
                "karaoke": 0,
                "forced": 0,
                "hearing_impaired": 0,
                "visual_impaired": 0,
                "clean_effects": 0,
                "attached_pic": 0,
                "timed_thumbnails": 0,
                "non_diegetic": 0,
                "captions": 0,
                "descriptions": 0,
                "metadata": 0,
                "dependent": 0,
                "still_image": 0
            }
        }
    ],
    "format": {
        "filename": "/Users/austinfranklin/Desktop/Code/Patches/Max/Externals/airPnP-master/MIR/FMP-Notebook/data/C3/FMP_C3S3_Schumann_Op15No7_Traeumerei_ColliardLigoratti.wav",
        "nb_streams": 1,
        "nb_programs": 0,
        "format_name": "wav",
        "format_long_name": "WAV / WAVE (Waveform Audio)",
        "duration": "46.694150",
        "size": "4118468",
        "bit_rate": "705607",
        "probe_score": 99
    }
},
                        "path": "/Users/austinfranklin/Desktop/Code/Patches/Max/Externals/airPnP-master/MIR/FMP-Notebook/data/C3/FMP_C3S3_Schumann_Op15No7_Traeumerei_ColliardLigoratti.wav",
                        "analysis": [ 0.187001, 2.91527, 0.182396, 13.3477, 0.331333, 584.656, 0.0300067, 0.0584233, 0.13248, 0.226042 ]
                    }
