
                    {
                        "metadata": {
    "streams": [
        {
            "index": 0,
            "codec_name": "mp3",
            "codec_long_name": "MP3 (MPEG audio layer 3)",
            "codec_type": "audio",
            "codec_tag_string": "[0][0][0][0]",
            "codec_tag": "0x0000",
            "sample_fmt": "fltp",
            "sample_rate": "44100",
            "channels": 1,
            "channel_layout": "mono",
            "bits_per_sample": 0,
            "initial_padding": 0,
            "r_frame_rate": "0/0",
            "avg_frame_rate": "0/0",
            "time_base": "1/14112000",
            "start_pts": 353600,
            "start_time": "0.025057",
            "duration_ts": 12533760,
            "duration": "0.888163",
            "bit_rate": "44073",
            "disposition": {
                "default": 0,
                "dub": 0,
                "original": 0,
                "comment": 0,
                "lyrics": 0,
                "karaoke": 0,
                "forced": 0,
                "hearing_impaired": 0,
                "visual_impaired": 0,
                "clean_effects": 0,
                "attached_pic": 0,
                "timed_thumbnails": 0,
                "non_diegetic": 0,
                "captions": 0,
                "descriptions": 0,
                "metadata": 0,
                "dependent": 0,
                "still_image": 0
            },
            "tags": {
                "encoder": "LAME3.99r"
            }
        }
    ],
    "format": {
        "filename": "/Users/austinfranklin/Desktop/Code/Javascript/Tone.js-dev/test/audio/hh.mp3",
        "nb_streams": 1,
        "nb_programs": 0,
        "format_name": "mp3",
        "format_long_name": "MP2/3 (MPEG audio layer 2/3)",
        "start_time": "0.025057",
        "duration": "0.888163",
        "size": "4975",
        "bit_rate": "44811",
        "probe_score": 51,
        "tags": {
            "encoder": "LAME 32bits version 3.99.5 (http://lame.sf.net)",
            "TLEN": "841"
        }
    }
},
                        "path": "/Users/austinfranklin/Desktop/Code/Javascript/Tone.js-dev/test/audio/hh.mp3",
                        "analysis": [ 0.2673, 32.1362, 0.546412, 4656.96, 0.504602, 5.55156, 0.0130594, 0.0262138, 0.431922, 0.329167 ]
                    }
