
                    {
                        "metadata": {
    "streams": [
        {
            "index": 0,
            "codec_name": "pcm_f24le",
            "codec_long_name": "PCM 24.0 floating point little-endian",
            "codec_type": "audio",
            "codec_tag_string": "[1][0][0][0]",
            "codec_tag": "0x0001",
            "sample_fmt": "flt",
            "sample_rate": "48000",
            "channels": 2,
            "channel_layout": "stereo",
            "bits_per_sample": 32,
            "initial_padding": 0,
            "r_frame_rate": "0/0",
            "avg_frame_rate": "0/0",
            "time_base": "1/48000",
            "duration_ts": 2,
            "duration": "0.000042",
            "bit_rate": "3072000",
            "disposition": {
                "default": 0,
                "dub": 0,
                "original": 0,
                "comment": 0,
                "lyrics": 0,
                "karaoke": 0,
                "forced": 0,
                "hearing_impaired": 0,
                "visual_impaired": 0,
                "clean_effects": 0,
                "attached_pic": 0,
                "timed_thumbnails": 0,
                "non_diegetic": 0,
                "captions": 0,
                "descriptions": 0,
                "metadata": 0,
                "dependent": 0,
                "still_image": 0
            }
        }
    ],
    "format": {
        "filename": "/Users/austinfranklin/.cargo/registry/src/github.com-1ecc6299db9ec823/hound-3.5.0/testsamples/waveformatextensible-24bit-4byte-48kHz-stereo.wav",
        "nb_streams": 1,
        "nb_programs": 0,
        "format_name": "wav",
        "format_long_name": "WAV / WAVE (Waveform Audio)",
        "duration": "0.000042",
        "size": "84",
        "bit_rate": "16000000",
        "probe_score": 99
    }
},
                        "path": "/Users/austinfranklin/.cargo/registry/src/github.com-1ecc6299db9ec823/hound-3.5.0/testsamples/waveformatextensible-24bit-4byte-48kHz-stereo.wav",
                        "analysis": [ 0.0001, 1, 0, 1, 0, 0, 0, 0, 0, 0.947917 ]
                    }
